perspective_bi/__init__.py
perspective_bi/charts.py
perspective_bi/dataset.py
perspective_bi-0.1.0.dist-info/LICENSE
perspective_bi-0.1.0.dist-info/METADATA
perspective_bi-0.1.0.dist-info/WHEEL
perspective_bi-0.1.0.dist-info/top_level.txt
perspective_bi-0.1.0.dist-info/RECORD
