Metadata-Version: 2.1
Name: perspective-bi
Version: 0.1.0
Summary: A declarative business intelligence library designed for natural language interactions
Home-page: https://github.com/perspective-bi/perspective-bi
Author: Robert Ritz
Classifier: Development Status :: 3 - Alpha
Classifier: Intended Audience :: Developers
Classifier: Topic :: Scientific/Engineering :: Visualization
Classifier: Programming Language :: Python :: 3
Classifier: License :: OSI Approved :: MIT License
Requires-Python: >=3.8
License-File: LICENSE
Requires-Dist: pandas>=2.0.0
Requires-Dist: plotly>=5.13.0
Requires-Dist: numpy>=1.24.0
Requires-Dist: python-dateutil>=2.8.2
